gestualis/__init__.py
gestualis-0.1.0.dist-info/METADATA
gestualis-0.1.0.dist-info/WHEEL
gestualis-0.1.0.dist-info/top_level.txt
gestualis-0.1.0.dist-info/RECORD
