Metadata-Version: 2.1
Name: gestualis
Version: 0.1.0
Summary: Gestualis is an AI-driven framework that interprets sign language from visual sources, converting it into spoken or written language in real time. Using advanced computer vision and deep learning, it accurately recognizes hand gestures, facial expressions, and body movements for precise translation. Adaptable for accessibility tools, real-time translation, and education, it also supports user-defined signs, ensuring inclusivity across linguistic regions.
Home-page: https://github.com/iamsurjog/Gestualis
Author: Sujatro Ganguli
Author-email: Sujatro Ganguli <iamsurjog@gmail.com>
Requires-Python: >=3.11
Requires-Dist: opencv-python
Requires-Dist: mediapipe
